pycarlanet/CarlanetActor.py
pycarlanet/CarlanetEventListener.py
pycarlanet/CarlanetManager.py
pycarlanet/__init__.py
pycarlanet/utils/__init__.py
pycarlanet/utils/decorators.py
pycarlanet-0.9.1a0.dist-info/LICENSE
pycarlanet-0.9.1a0.dist-info/METADATA
pycarlanet-0.9.1a0.dist-info/WHEEL
pycarlanet-0.9.1a0.dist-info/top_level.txt
pycarlanet-0.9.1a0.dist-info/RECORD
