Metadata-Version: 2.1
Name: pycarlanet
Version: 0.9.1a0
Author: Valerio Cislaghi, Christian Quadri
License: MIT
Project-URL: Source, https://github.com/jaivra/pycarlanet
Requires-Python: >=2.7,!=3.0.*,!=3.1.*,!=3.2.*,!=3.3.*,!=3.4.*,!=3.5.*,<3.9
License-File: LICENSE
Requires-Dist: pyzmq ==23.2.1
Requires-Dist: carla ==0.9.13
